promptlearn/__init__.py
promptlearn/base.py
promptlearn/classifier.py
promptlearn/regressor.py
promptlearn/utils.py
promptlearn/version.py
promptlearn-0.3.0.dist-info/licenses/LICENSE
tests/__init__.py
tests/test_base_and_utils.py
tests/test_classifier.py
tests/test_regressor.py
promptlearn-0.3.0.dist-info/METADATA
promptlearn-0.3.0.dist-info/WHEEL
promptlearn-0.3.0.dist-info/top_level.txt
promptlearn-0.3.0.dist-info/RECORD
