Metadata-Version: 2.4
Name: promptlearn
Version: 0.3.0
Summary: LLM-powered estimators for scikit-learn pipelines
Home-page: https://github.com/frlinaker/promptlearn
Author: Fredrik Linaker
Author-email: fredrik.linaker@gmail.com
License: MIT
Classifier: License :: OSI Approved :: MIT License
Classifier: Programming Language :: Python :: 3
Classifier: Intended Audience :: Developers
Classifier: Topic :: Scientific/Engineering :: Artificial Intelligence
Requires-Python: >=3.8
License-File: LICENSE
Requires-Dist: scikit-learn
Requires-Dist: openai
Requires-Dist: pandas
Requires-Dist: numpy
Requires-Dist: joblib
Dynamic: author
Dynamic: author-email
Dynamic: classifier
Dynamic: description
Dynamic: description-content-type
Dynamic: home-page
Dynamic: license
Dynamic: license-file
Dynamic: requires-dist
Dynamic: requires-python
Dynamic: summary
